{
  "pdf_file": "2a32bd733b78cae348e7cfb3c6402919_240724_Mail_wethouders_windbeleid.pdf",
  "pdf_content": "1Van:    \nVerzonden:  woensdag  24 juli 2024 15:47 \nAan:   \nOnderwerp:  Windbeleid  \nGeachte wethouders  duurzaamheid,  partners in de RES \nCc: ambtenaren  duurzaamheid  \nVaststelling  van het windbeleid \nGedeputeerde  Staten hebben  in de vergadering  van 17 juli 2024 het definitieve  windbeleid  vastgesteld,  onder \nvoorbehoud  van vaststelling  van de instructieregel  wind door  Provinciale  Staten op 9 oktober  2024. Via bijgaande  link \nvindt u de relevante  stukken. \nstatenvoorstel_PS24 ‐000439 (notubiz.nl)  \nontwerpbesluit_PS24‐000439  \n/Bijlage+II+Reactienota+windbeleid+provincie+Overijssel  \nOER+Fase+2a  \ngewijzigde+vaststelling+instructieregel+windenergie  \nHandreiking+Wind  \nPPE+2024  \nVast\nstelling van het maximum  GWh voor gemeente  zonder programmeringsafspraken  \nEnkele  gemeenten  hebben geen programmeringsafspraken  gemaakt.  Door geen maximum  vast te stellen  is de hele \ngemeente  zoekgebied  tot dat het provinciaal  maximum  is bereikt. Dit brengt onzekerheid  naar inwoners  met zich mee. \nOm hieraan tegemoet  te komen heeft GS een maximum  voor deze  gemeenten  bepaald aan de hand  van de technische  \npotentie  van het grondgebied  van de betreffende  gemeente.  Ook dit is verwerkt in het PPE.  \nBespreking  van de instructieregel  windenergie  door Provinciale  Staten \nWij he bben de indieners va n zienswijzen geattendeerd op de mo gelijkheid om gebruik te maken van het spreekrecht tijdens \nde verg adering van de Statencommissi e Milieu & Energi e van 18 september 2024. Voor het horen van indieners van \nzienswijzen wordt e en hele dag uitgetrokken.  Op 25 s eptember 2024 vind t de inhoudelijke bespreki ng van h et \nstatenvoorstel plaats in de vergadering van de Statencommissi e Milieu & E nergie. Indieners van zienswij zen zijn welkom als \ntoehoo rder bij deze verg adering. Op 9 oktobe r 2024 besluiten Pr ovinciale S taten op het voorstel.\nInwerkingtreding  van het windbeleid  \nHet Provinciaal  Programma  Energiestrategie  en de Handreiking  wind en zon publiceren  wij dan ook op 15 oktober  2024. \nDe inwerkingtreding  hebben  wij gepland op 16 oktober 2024. \nOpenstelling  van de gebieden  \nWe hebben gepland de eerste gebieden  open te stellen per 16 oktober 2024. Voordat wij dat doen nemen  wij contact \nop met de betreffende  gemeenten  om  te bespreken  hoe we de communicatie  met de inwoners  van het gebied samen \ngaan oppakken.  In het gesprek komt ook aan de orde hoe wij na sluiting van de openstelling  de aanvragen  selecteren.  \nMet vriendelijke groet,  \n\n2  \n \n  \nteam Nieuwe Energie| ma,di,wo,do,vrij |  \nProvincie Overijssel | Postbus 10078 | 8000 GB Zwolle  \n  \n             \n                   \n  \n",
  "metadata": {
    "Titel": "Mail aan Overijsselse wethouders over het windbeleid 24 juli 2024",
    "Samenvatting": "Gedeputeerde Staten hebben in de vergadering van 17 juli 2024 het definitieve windbeleid vastgesteld, onder voorbehoud van vaststelling van de instructieregel wind door Provinciale Staten op 9 oktober 2024. Met deze mail worden de Overijsselse duurzaamheidswethouders hiervan op de hoogte gebracht.",
    "Creatie jaar": "2024",
    "WOO thema's": "wet of algemeen verbindend voorschrift"
  }
}